cpacspy/__init__.py
cpacspy/__version__.py
cpacspy/aeromap.py
cpacspy/aircraft.py
cpacspy/cpacsfunctions.py
cpacspy/cpacspy.py
cpacspy/rotorcraft.py
cpacspy/utils.py
cpacspy-0.2.0.dist-info/licenses/LICENSE.txt
cpacspy-0.2.0.dist-info/METADATA
cpacspy-0.2.0.dist-info/WHEEL
cpacspy-0.2.0.dist-info/top_level.txt
cpacspy-0.2.0.dist-info/RECORD
