Metadata-Version: 2.4
Name: cpacspy
Version: 0.2.0
Summary: PyPI package to work with CPACS file and AeroMaps
Home-page: https://github.com/cfsengineering/cpacspy
Author: Giacomo Benedetti
Author-email: giacomo.benedetti@cfse.ch
License: Apache License 2.0
Keywords: CPACS,aircraft,design,xml,aerodynamics,coefficients,databases
Classifier: Programming Language :: Python :: 3
Classifier: Programming Language :: Python :: 3.11
Classifier: License :: OSI Approved :: Apache Software License
Classifier: Operating System :: OS Independent
Classifier: Intended Audience :: Developers
Requires-Python: >=3.11
License-File: LICENSE.txt
Dynamic: author
Dynamic: author-email
Dynamic: classifier
Dynamic: description
Dynamic: description-content-type
Dynamic: home-page
Dynamic: keywords
Dynamic: license
Dynamic: license-file
Dynamic: requires-python
Dynamic: summary
